{"players": [{"account_id": 1025177833, "player_slot": 0, "team_number": 0, "team_slot": 0, "hero_id": 107, "hero_variant": 3, "item_0": 63, "item_1": 100, "item_2": 267, "item_3": 36, "item_4": 188, "item_5": 0, "backpack_0": 38, "backpack_1": 4204, "backpack_2": 0, "item_neutral": 1641, "item_neutral2": 1583, "kills": 3, "deaths": 4, "assists": 15, "leaver_status": 3, "last_hits": 41, "denies": 0, "gold_per_min": 229, "xp_per_min": 506, "level": 23, "net_worth": 7376, "aghanims_scepter": 0, "aghanims_shard": 0, "moonshard": 0, "hero_damage": 13835, "tower_damage": 0, "hero_healing": 240, "gold": 1, "gold_spent": 9715, "ability_upgrades_arr": [5608, 5609, 5610, 5610, 5609, 5612, 5609, 5609, 5610, 324, 5610, 5608, 5608, 5608, 5612, 6640, 5612, 977], "personaname": "Kikeberto", "name": null, "last_login": null, "rank_tier": 55, "computed_mmr": 4058.2, "is_subscriber": false, "radiant_win": false, "start_time": 1760668522, "duration": 3470, "cluster": 251, "lobby_type": 0, "game_mode": 22, "is_contributor": false, "patch": 58, "region": 15, "isRadiant": true, "win": 0, "lose": 1, "total_gold": 13243, "total_xp": 29263, "kills_per_min": 0.05187319884726225, "kda": 3.6, "abandons": 1, "benchmarks": {"gold_per_min": {"raw": 229, "pct": 0.05221339387060159}, "xp_per_min": {"raw": 506, "pct": 0.3132803632236095}, "kills_per_min": {"raw": 0.05187319884726225, "pct": 0.12599318955732122}, "last_hits_per_min": {"raw": 0.7089337175792507, "pct": 0.046538024971623154}, "hero_damage_per_min": {"raw": 239.22190201729106, "pct": 0.056753688989784334}, "hero_healing_per_min": {"raw": 4.14985590778098, "pct": 0.5107832009080591}, "tower_damage": {"raw": 0, "pct": 0.25198637911464244}}}, {"player_slot": 1, "team_number": 0, "team_slot": 1, "hero_id": 8, "hero_variant": 2, "item_0": 147, "item_1": 152, "item_2": 174, "item_3": 135, "item_4": 63, "item_5": 145, "backpack_0": 4206, "backpack_1": 0, "backpack_2": 0, "item_neutral": 1643, "item_neutral2": 1584, "kills": 11, "deaths": 7, "assists": 6, "leaver_status": 0, "last_hits": 451, "denies": 11, "gold_per_min": 607, "xp_per_min": 847, "level": 27, "net_worth": 29058, "aghanims_scepter": 1, "aghanims_shard": 0, "moonshard": 0, "hero_damage": 45890, "tower_damage": 4643, "hero_healing": 3002, "gold": 2758, "gold_spent": 29310, "ability_upgrades_arr": [5028, 5027, 5027, 5029, 5027, 5030, 5028, 5027, 5028, 7021, 5028, 5029, 5030, 5029, 1192, 5029, 5030, 6105, 915, 628], "is_subscriber": false, "radiant_win": false, "start_time": 1760668522, "duration": 3470, "cluster": 251, "lobby_type": 0, "game_mode": 22, "is_contributor": false, "patch": 58, "region": 15, "isRadiant": true, "win": 0, "lose": 1, "total_gold": 35104, "total_xp": 48984, "kills_per_min": 0.19020172910662825, "kda": 2.13, "abandons": 0, "benchmarks": {"gold_per_min": {"raw": 607, "pct": 0.5504434589800443}, "xp_per_min": {"raw": 847, "pct": 0.5850886917960089}, "kills_per_min": {"raw": 0.19020172910662825, "pct": 0.49390243902439024}, "last_hits_per_min": {"raw": 7.798270893371758, "pct": 0.4465077605321508}, "hero_damage_per_min": {"raw": 793.4870317002882, "pct": 0.7466740576496674}, "hero_healing_per_min": {"raw": 51.90778097982709, "pct": 0.24750554323725055}, "tower_damage": {"raw": 4643, "pct": 0.5279933481152993}}}, {"player_slot": 2, "team_number": 0, "team_slot": 2, "hero_id": 71, "hero_variant": 1, "item_0": 249, "item_1": 154, "item_2": 73, "item_3": 141, "item_4": 63, "item_5": 116, "backpack_0": 0, "backpack_1": 0, "backpack_2": 0, "item_neutral": 1643, "item_neutral2": 1597, "kills": 9, "deaths": 7, "assists": 17, "leaver_status": 0, "last_hits": 319, "denies": 10, "gold_per_min": 546, "xp_per_min": 885, "level": 28, "net_worth": 26564, "aghanims_scepter": 0, "aghanims_shard": 0, "moonshard": 0, "hero_damage": 31675, "tower_damage": 0, "hero_healing": 0, "gold": 5309, "gold_spent": 22550, "ability_upgrades_arr": [5355, 5353, 7301, 5355, 5355, 5356, 5355, 5353, 5353, 5931, 5353, 5356, 7301, 7301, 6253, 7301, 5356, 8254, 6543, 7022, 6296], "is_subscriber": false, "radiant_win": false, "start_time": 1760668522, "duration": 3470, "cluster": 251, "lobby_type": 0, "game_mode": 22, "is_contributor": false, "patch": 58, "region": 15, "isRadiant": true, "win": 0, "lose": 1, "total_gold": 31577, "total_xp": 51182, "kills_per_min": 0.15561959654178673, "kda": 3.25, "abandons": 0, "benchmarks": {"gold_per_min": {"raw": 546, "pct": 0.9007483261126428}, "xp_per_min": {"raw": 885, "pct": 0.8651043717999213}, "kills_per_min": {"raw": 0.15561959654178675, "pct": 0.46258369436786134}, "last_hits_per_min": {"raw": 5.515850144092219, "pct": 0.9403308389129579}, "hero_damage_per_min": {"raw": 547.6945244956772, "pct": 0.6155966916108704}, "hero_healing_per_min": {"raw": 0, "pct": 0.6947617172115006}, "tower_damage": {"raw": 0, "pct": 0.24419062623079954}}}, {"player_slot": 3, "team_number": 0, "team_slot": 3, "hero_id": 31, "hero_variant": 2, "item_0": 180, "item_1": 256, "item_2": 277, "item_3": 108, "item_4": 36, "item_5": 0, "backpack_0": 0, "backpack_1": 0, "backpack_2": 0, "item_neutral": 1605, "item_neutral2": 1595, "kills": 6, "deaths": 8, "assists": 14, "leaver_status": 0, "last_hits": 89, "denies": 5, "gold_per_min": 318, "xp_per_min": 551, "level": 24, "net_worth": 16658, "aghanims_scepter": 0, "aghanims_shard": 1, "moonshard": 0, "hero_damage": 26885, "tower_damage": 332, "hero_healing": 0, "gold": 1908, "gold_spent": 16055, "ability_upgrades_arr": [5134, 7325, 5134, 5136, 5134, 5137, 5134, 7325, 5136, 7325, 5137, 7325, 5136, 5136, 6387, 5137, 775, 531], "is_subscriber": false, "radiant_win": false, "start_time": 1760668522, "duration": 3470, "cluster": 251, "lobby_type": 0, "game_mode": 22, "is_contributor": false, "patch": 58, "region": 15, "isRadiant": true, "win": 0, "lose": 1, "total_gold": 18391, "total_xp": 31866, "kills_per_min": 0.1037463976945245, "kda": 2.22, "abandons": 0, "benchmarks": {"gold_per_min": {"raw": 318, "pct": 0.3021408077687045}, "xp_per_min": {"raw": 551, "pct": 0.4526594570734937}, "kills_per_min": {"raw": 0.1037463976945245, "pct": 0.37828293974839994}, "last_hits_per_min": {"raw": 1.5389048991354466, "pct": 0.4793643787243434}, "hero_damage_per_min": {"raw": 464.87031700288185, "pct": 0.4608254248510263}, "hero_healing_per_min": {"raw": 0, "pct": 0.6685058485985433}, "tower_damage": {"raw": 332, "pct": 0.5526373868903112}}}, {"player_slot": 4, "team_number": 0, "team_slot": 4, "hero_id": 104, "hero_variant": 1, "item_0": 1, "item_1": 127, "item_2": 50, "item_3": 112, "item_4": 152, "item_5": 108, "backpack_0": 0, "backpack_1": 0, "backpack_2": 0, "item_neutral": 1643, "item_neutral2": 1594, "kills": 4, "deaths": 11, "assists": 10, "leaver_status": 0, "last_hits": 294, "denies": 10, "gold_per_min": 425, "xp_per_min": 613, "level": 25, "net_worth": 21627, "aghanims_scepter": 0, "aghanims_shard": 1, "moonshard": 0, "hero_damage": 24200, "tower_damage": 1453, "hero_healing": 1282, "gold": 1402, "gold_spent": 23610, "ability_upgrades_arr": [5595, 5596, 5597, 5595, 5595, 5598, 5595, 5596, 5596, 1113, 5596, 5598, 5597, 5597, 6671, 5597, 5598, 7395, 925], "is_subscriber": false, "radiant_win": false, "start_time": 1760668522, "duration": 3470, "cluster": 251, "lobby_type": 0, "game_mode": 22, "is_contributor": false, "patch": 58, "region": 15, "isRadiant": true, "win": 0, "lose": 1, "total_gold": 24579, "total_xp": 35451, "kills_per_min": 0.06916426512968299, "kda": 1.17, "abandons": 0, "benchmarks": {"gold_per_min": {"raw": 425, "pct": 0.28236272878535773}, "xp_per_min": {"raw": 613, "pct": 0.35124792013311146}, "kills_per_min": {"raw": 0.069164265129683, "pct": 0.08402662229617304}, "last_hits_per_min": {"raw": 5.083573487031701, "pct": 0.610648918469218}, "hero_damage_per_min": {"raw": 418.4438040345821, "pct": 0.13926788685524127}, "hero_healing_per_min": {"raw": 22.1671469740634, "pct": 0.3752079866888519}, "tower_damage": {"raw": 1453, "pct": 0.44575707154742095}}}, {"player_slot": 128, "team_number": 1, "team_slot": 0, "hero_id": 42, "hero_variant": 2, "item_0": 50, "item_1": 116, "item_2": 208, "item_3": 168, "item_4": 112, "item_5": 137, "backpack_0": 218, "backpack_1": 4206, "backpack_2": 4206, "item_neutral": 1643, "item_neutral2": 1597, "kills": 8, "deaths": 4, "assists": 10, "leaver_status": 0, "last_hits": 595, "denies": 8, "gold_per_min": 736, "xp_per_min": 1134, "level": 30, "net_worth": 40830, "aghanims_scepter": 1, "aghanims_shard": 1, "moonshard": 0, "hero_damage": 45808, "tower_damage": 15113, "hero_healing": 0, "gold": 8305, "gold_spent": 33730, "ability_upgrades_arr": [5088, 5086, 1282, 5088, 5086, 5089, 1282, 5088, 5088, 5086, 1282, 5089, 1282, 5086, 5976, 1545, 5089, 5908, 6566, 6088, 809, 1547, 741], "is_subscriber": false, "radiant_win": false, "start_time": 1760668522, "duration": 3470, "cluster": 251, "lobby_type": 0, "game_mode": 22, "is_contributor": false, "patch": 58, "region": 15, "isRadiant": false, "win": 1, "lose": 0, "total_gold": 42565, "total_xp": 65583, "kills_per_min": 0.13832853025936598, "kda": 3.6, "abandons": 0, "benchmarks": {"gold_per_min": {"raw": 736, "pct": 0.8833333333333333}, "xp_per_min": {"raw": 1134, "pct": 0.909106529209622}, "kills_per_min": {"raw": 0.138328530259366, "pct": 0.2711340206185567}, "last_hits_per_min": {"raw": 10.288184438040346, "pct": 0.9486254295532646}, "hero_damage_per_min": {"raw": 792.0691642651298, "pct": 0.5426116838487972}, "hero_healing_per_min": {"raw": 0, "pct": 0.9589347079037801}, "tower_damage": {"raw": 15113, "pct": 0.9104810996563574}}}, {"account_id": 45421382, "player_slot": 129, "team_number": 1, "team_slot": 1, "hero_id": 41, "hero_variant": 2, "item_0": 123, "item_1": 139, "item_2": 108, "item_3": 1097, "item_4": 147, "item_5": 117, "backpack_0": 0, "backpack_1": 0, "backpack_2": 63, "item_neutral": 828, "item_neutral2": 1586, "kills": 6, "deaths": 8, "assists": 17, "leaver_status": 0, "last_hits": 417, "denies": 13, "gold_per_min": 576, "xp_per_min": 852, "level": 27, "net_worth": 29686, "aghanims_scepter": 0, "aghanims_shard": 1, "moonshard": 0, "hero_damage": 26099, "tower_damage": 6351, "hero_healing": 0, "gold": 1486, "gold_spent": 32675, "ability_upgrades_arr": [5182, 5184, 5182, 5184, 5182, 5185, 5691, 5184, 5182, 5184, 856, 5185, 5691, 5691, 6807, 5691, 5185, 6128, 7001, 867], "personaname": "La Chaucha", "name": null, "last_login": "2026-03-03T14:36:01.200Z", "rank_tier": 42, "computed_mmr": 4031.51, "is_subscriber": false, "radiant_win": false, "start_time": 1760668522, "duration": 3470, "cluster": 251, "lobby_type": 0, "game_mode": 22, "is_contributor": false, "patch": 58, "region": 15, "isRadiant": false, "win": 1, "lose": 0, "total_gold": 33312, "total_xp": 49274, "kills_per_min": 0.1037463976945245, "kda": 2.56, "abandons": 0, "benchmarks": {"gold_per_min": {"raw": 576, "pct": 0.5507246376811594}, "xp_per_min": {"raw": 852, "pct": 0.5987795575896262}, "kills_per_min": {"raw": 0.1037463976945245, "pct": 0.2341723874904653}, "last_hits_per_min": {"raw": 7.210374639769452, "pct": 0.5484363081617086}, "hero_damage_per_min": {"raw": 451.27953890489914, "pct": 0.41685736079328756}, "hero_healing_per_min": {"raw": 0, "pct": 0.9462242562929062}, "tower_damage": {"raw": 6351, "pct": 0.65255530129672}}}, {"account_id": 65137360, "player_slot": 130, "team_number": 1, "team_slot": 2, "hero_id": 123, "hero_variant": 1, "item_0": 40, "item_1": 0, "item_2": 215, "item_3": 100, "item_4": 1466, "item_5": 231, "backpack_0": 38, "backpack_1": 4204, "backpack_2": 0, "item_neutral": 1608, "item_neutral2": 1583, "kills": 3, "deaths": 10, "assists": 25, "leaver_status": 0, "last_hits": 77, "denies": 8, "gold_per_min": 346, "xp_per_min": 739, "level": 26, "net_worth": 17464, "aghanims_scepter": 0, "aghanims_shard": 0, "moonshard": 0, "hero_damage": 17540, "tower_damage": 1262, "hero_healing": 954, "gold": 2654, "gold_spent": 17010, "ability_upgrades_arr": [8429, 8158, 8429, 9501, 8158, 8106, 8158, 9501, 8429, 8158, 7132, 8106, 8429, 9501, 9513, 9501, 8106, 7383, 1134], "personaname": "PatoDeGoma", "name": null, "last_login": "2021-02-10T20:32:57.535Z", "rank_tier": 45, "computed_mmr": null, "is_subscriber": false, "radiant_win": false, "start_time": 1760668522, "duration": 3470, "cluster": 251, "lobby_type": 0, "game_mode": 22, "is_contributor": false, "patch": 58, "region": 15, "isRadiant": false, "win": 1, "lose": 0, "total_gold": 20010, "total_xp": 42738, "kills_per_min": 0.05187319884726225, "kda": 2.55, "abandons": 0, "benchmarks": {"gold_per_min": {"raw": 346, "pct": 0.36620294599018005}, "xp_per_min": {"raw": 739, "pct": 0.7745499181669394}, "kills_per_min": {"raw": 0.05187319884726225, "pct": 0.11211129296235679}, "last_hits_per_min": {"raw": 1.3314121037463977, "pct": 0.17798690671031098}, "hero_damage_per_min": {"raw": 303.28530259365994, "pct": 0.10556464811783961}, "hero_healing_per_min": {"raw": 16.495677233429394, "pct": 0.8776595744680851}, "tower_damage": {"raw": 1262, "pct": 0.705810147299509}}}, {"account_id": 115132074, "player_slot": 131, "team_number": 1, "team_slot": 3, "hero_id": 35, "hero_variant": 2, "item_0": 172, "item_1": 135, "item_2": 158, "item_3": 263, "item_4": 160, "item_5": 63, "backpack_0": 0, "backpack_1": 0, "backpack_2": 0, "item_neutral": 1643, "item_neutral2": 1577, "kills": 15, "deaths": 7, "assists": 12, "leaver_status": 0, "last_hits": 437, "denies": 28, "gold_per_min": 646, "xp_per_min": 813, "level": 27, "net_worth": 34979, "aghanims_scepter": 0, "aghanims_shard": 1, "moonshard": 1, "hero_damage": 49041, "tower_damage": 8545, "hero_healing": 0, "gold": 5529, "gold_spent": 31000, "ability_upgrades_arr": [5155, 5156, 5155, 5154, 5155, 5157, 5155, 5156, 5154, 5154, 5154, 5157, 5156, 5156, 928, 7892, 5157, 6897, 6896, 7396], "personaname": "Durotan", "name": null, "last_login": null, "rank_tier": 41, "computed_mmr": 3905.19, "is_subscriber": false, "radiant_win": false, "start_time": 1760668522, "duration": 3470, "cluster": 251, "lobby_type": 0, "game_mode": 22, "is_contributor": false, "patch": 58, "region": 15, "isRadiant": false, "win": 1, "lose": 0, "total_gold": 37360, "total_xp": 47018, "kills_per_min": 0.25936599423631124, "kda": 3.38, "abandons": 0, "benchmarks": {"gold_per_min": {"raw": 646, "pct": 0.7315570358034971}, "xp_per_min": {"raw": 813, "pct": 0.6749375520399667}, "kills_per_min": {"raw": 0.25936599423631124, "pct": 0.5587010824313072}, "last_hits_per_min": {"raw": 7.556195965417867, "pct": 0.6992506244796003}, "hero_damage_per_min": {"raw": 847.9711815561959, "pct": 0.5200666111573689}, "hero_healing_per_min": {"raw": 0, "pct": 0.9365528726061615}, "tower_damage": {"raw": 8545, "pct": 0.6825978351373855}}}, {"player_slot": 132, "team_number": 1, "team_slot": 4, "hero_id": 26, "hero_variant": 1, "item_0": 214, "item_1": 43, "item_2": 40, "item_3": 108, "item_4": 77, "item_5": 176, "backpack_0": 4205, "backpack_1": 0, "backpack_2": 0, "item_neutral": 1639, "item_neutral2": 1595, "kills": 4, "deaths": 7, "assists": 11, "leaver_status": 0, "last_hits": 27, "denies": 1, "gold_per_min": 264, "xp_per_min": 542, "level": 23, "net_worth": 14426, "aghanims_scepter": 0, "aghanims_shard": 0, "moonshard": 0, "hero_damage": 7520, "tower_damage": 0, "hero_healing": 0, "gold": 2986, "gold_spent": 12320, "ability_upgrades_arr": [5044, 5046, 5046, 5045, 5046, 5047, 5044, 5044, 5045, 5044, 5045, 5047, 5045, 465, 5046, 401, 5047, 777], "is_subscriber": false, "radiant_win": false, "start_time": 1760668522, "duration": 3470, "cluster": 251, "lobby_type": 0, "game_mode": 22, "is_contributor": false, "patch": 58, "region": 15, "isRadiant": false, "win": 1, "lose": 0, "total_gold": 15268, "total_xp": 31345, "kills_per_min": 0.06916426512968299, "kda": 1.88, "abandons": 0, "benchmarks": {"gold_per_min": {"raw": 264, "pct": 0.18487278761061948}, "xp_per_min": {"raw": 542, "pct": 0.4788440265486726}, "kills_per_min": {"raw": 0.069164265129683, "pct": 0.19261615044247787}, "last_hits_per_min": {"raw": 0.46685878962536026, "pct": 0.06747787610619468}, "hero_damage_per_min": {"raw": 130.02881844380403, "pct": 0.014103982300884955}, "hero_healing_per_min": {"raw": 0, "pct": 0.7679756637168141}, "tower_damage": {"raw": 0, "pct": 0.265625}}}], "radiant_win": false, "duration": 3470, "pre_game_duration": 90, "start_time": 1760668522, "match_id": 8514678567, "match_seq_num": 7151799917, "tower_status_radiant": 0, "tower_status_dire": 1958, "barracks_status_radiant": 0, "barracks_status_dire": 63, "cluster": 251, "first_blood_time": 174, "lobby_type": 0, "human_players": 10, "leagueid": 0, "game_mode": 22, "flags": 1, "engine": 1, "radiant_score": 36, "dire_score": 37, "picks_bans": [{"is_pick": true, "hero_id": 123, "team": 1, "order": 0}, {"is_pick": true, "hero_id": 31, "team": 0, "order": 1}, {"is_pick": true, "hero_id": 35, "team": 1, "order": 2}, {"is_pick": true, "hero_id": 107, "team": 0, "order": 3}, {"is_pick": true, "hero_id": 42, "team": 1, "order": 4}, {"is_pick": true, "hero_id": 8, "team": 0, "order": 5}, {"is_pick": true, "hero_id": 41, "team": 1, "order": 6}, {"is_pick": true, "hero_id": 104, "team": 0, "order": 7}, {"is_pick": true, "hero_id": 26, "team": 1, "order": 8}, {"is_pick": true, "hero_id": 71, "team": 0, "order": 9}, {"is_pick": false, "hero_id": 59, "team": 0, "order": 10}, {"is_pick": false, "hero_id": 70, "team": 0, "order": 11}, {"is_pick": false, "hero_id": 88, "team": 0, "order": 12}, {"is_pick": false, "hero_id": 81, "team": 0, "order": 13}, {"is_pick": false, "hero_id": 93, "team": 0, "order": 14}], "od_data": {"has_api": true, "has_gcdata": false, "has_parsed": false, "has_archive": false}, "metadata": null, "patch": 58, "region": 15}