{"players": [{"player_slot": 0, "team_number": 0, "team_slot": 0, "hero_id": 64, "hero_variant": 3, "item_0": 0, "item_1": 100, "item_2": 90, "item_3": 42, "item_4": 108, "item_5": 0, "backpack_0": 0, "backpack_1": 0, "backpack_2": 0, "item_neutral": 1602, "item_neutral2": 1577, "kills": 3, "deaths": 10, "assists": 14, "leaver_status": 0, "last_hits": 98, "denies": 9, "gold_per_min": 334, "xp_per_min": 441, "level": 18, "net_worth": 11525, "aghanims_scepter": 0, "aghanims_shard": 0, "moonshard": 0, "hero_damage": 26269, "tower_damage": 831, "hero_healing": 0, "gold": 900, "gold_spent": 13965, "ability_upgrades_arr": [5297, 5299, 5297, 5299, 5297, 5300, 5297, 5299, 5298, 303, 5298, 5300, 1317, 5298, 526, 5298, 5300], "is_subscriber": false, "radiant_win": false, "start_time": 1763684619, "duration": 2571, "cluster": 346, "lobby_type": 0, "game_mode": 22, "is_contributor": false, "patch": 58, "region": 38, "isRadiant": true, "win": 0, "lose": 1, "total_gold": 14311, "total_xp": 18896, "kills_per_min": 0.07001166861143523, "kda": 1.55, "abandons": 0, "benchmarks": {"gold_per_min": {"raw": 334, "pct": 0.40683229813664595}, "xp_per_min": {"raw": 441, "pct": 0.2841614906832298}, "kills_per_min": {"raw": 0.07001166861143523, "pct": 0.306832298136646}, "last_hits_per_min": {"raw": 2.2870478413068844, "pct": 0.6192546583850932}, "hero_damage_per_min": {"raw": 613.0455075845974, "pct": 0.8552795031055901}, "hero_healing_per_min": {"raw": 0, "pct": 0.5785714285714286}, "tower_damage": {"raw": 831, "pct": 0.3847826086956522}}}, {"player_slot": 1, "team_number": 0, "team_slot": 1, "hero_id": 14, "hero_variant": 3, "item_0": 116, "item_1": 125, "item_2": 90, "item_3": 50, "item_4": 40, "item_5": 1, "backpack_0": 0, "backpack_1": 0, "backpack_2": 0, "item_neutral": 565, "item_neutral2": 1585, "kills": 9, "deaths": 13, "assists": 9, "leaver_status": 0, "last_hits": 152, "denies": 10, "gold_per_min": 433, "xp_per_min": 644, "level": 22, "net_worth": 14184, "aghanims_scepter": 0, "aghanims_shard": 0, "moonshard": 0, "hero_damage": 21598, "tower_damage": 525, "hero_healing": 0, "gold": 599, "gold_spent": 15590, "ability_upgrades_arr": [5076, 5075, 5076, 5074, 5076, 5077, 5076, 5075, 5075, 5075, 5074, 5077, 5074, 5074, 6565, 5932, 5077, 332], "is_subscriber": false, "radiant_win": false, "start_time": 1763684619, "duration": 2571, "cluster": 346, "lobby_type": 0, "game_mode": 22, "is_contributor": false, "patch": 58, "region": 38, "isRadiant": true, "win": 0, "lose": 1, "total_gold": 18554, "total_xp": 27595, "kills_per_min": 0.2100350058343057, "kda": 1.29, "abandons": 0, "benchmarks": {"gold_per_min": {"raw": 433, "pct": 0.7070095191000124}, "xp_per_min": {"raw": 644, "pct": 0.6172580046977376}, "kills_per_min": {"raw": 0.21003500583430573, "pct": 0.6583013969588329}, "last_hits_per_min": {"raw": 3.547257876312719, "pct": 0.7455804178514032}, "hero_damage_per_min": {"raw": 504.0373395565927, "pct": 0.5364074669303993}, "hero_healing_per_min": {"raw": 0, "pct": 0.7490419087649894}, "tower_damage": {"raw": 525, "pct": 0.5924094449252071}}}, {"account_id": 181295737, "player_slot": 2, "team_number": 0, "team_slot": 2, "hero_id": 9, "hero_variant": 3, "item_0": 100, "item_1": 180, "item_2": 267, "item_3": 43, "item_4": 36, "item_5": 237, "backpack_0": 0, "backpack_1": 0, "backpack_2": 0, "item_neutral": 1605, "item_neutral2": 1576, "kills": 6, "deaths": 11, "assists": 12, "leaver_status": 0, "last_hits": 89, "denies": 3, "gold_per_min": 334, "xp_per_min": 396, "level": 17, "net_worth": 9905, "aghanims_scepter": 0, "aghanims_shard": 1, "moonshard": 0, "hero_damage": 20344, "tower_damage": 318, "hero_healing": 0, "gold": 1215, "gold_spent": 10045, "ability_upgrades_arr": [5048, 5051, 5050, 5051, 5051, 1213, 5051, 5048, 5048, 5048, 817, 1213, 5050, 5050, 6013, 5050], "personaname": "SpAwN", "name": null, "last_login": null, "rank_tier": 34, "computed_mmr": 4082.21, "is_subscriber": false, "radiant_win": false, "start_time": 1763684619, "duration": 2571, "cluster": 346, "lobby_type": 0, "game_mode": 22, "is_contributor": false, "patch": 58, "region": 38, "isRadiant": true, "win": 0, "lose": 1, "total_gold": 14311, "total_xp": 16968, "kills_per_min": 0.14002333722287047, "kda": 1.5, "abandons": 0, "benchmarks": {"gold_per_min": {"raw": 334, "pct": 0.2662203913491246}, "xp_per_min": {"raw": 396, "pct": 0.15190525231719876}, "kills_per_min": {"raw": 0.14002333722287047, "pct": 0.5169927909371782}, "last_hits_per_min": {"raw": 2.077012835472579, "pct": 0.27188465499485065}, "hero_damage_per_min": {"raw": 474.77246207701285, "pct": 0.5319258496395468}, "hero_healing_per_min": {"raw": 0, "pct": 0.6091658084449022}, "tower_damage": {"raw": 318, "pct": 0.3269824922760041}}}, {"player_slot": 3, "team_number": 0, "team_slot": 3, "hero_id": 102, "hero_variant": 3, "item_0": 11, "item_1": 50, "item_2": 36, "item_3": 154, "item_4": 143, "item_5": 4, "backpack_0": 0, "backpack_1": 0, "backpack_2": 0, "item_neutral": 1603, "item_neutral2": 1586, "kills": 1, "deaths": 9, "assists": 12, "leaver_status": 0, "last_hits": 104, "denies": 2, "gold_per_min": 294, "xp_per_min": 484, "level": 19, "net_worth": 11447, "aghanims_scepter": 0, "aghanims_shard": 0, "moonshard": 0, "hero_damage": 20061, "tower_damage": 0, "hero_healing": 440, "gold": 1772, "gold_spent": 9985, "ability_upgrades_arr": [5586, 5587, 5586, 5587, 5586, 5588, 5586, 5587, 5587, 1165, 5585, 5588, 5585, 5585, 7340, 5585, 5588], "is_subscriber": false, "radiant_win": false, "start_time": 1763684619, "duration": 2571, "cluster": 346, "lobby_type": 0, "game_mode": 22, "is_contributor": false, "patch": 58, "region": 38, "isRadiant": true, "win": 0, "lose": 1, "total_gold": 12597, "total_xp": 20739, "kills_per_min": 0.023337222870478413, "kda": 1.3, "abandons": 0, "benchmarks": {"gold_per_min": {"raw": 294, "pct": 0.223731884057971}, "xp_per_min": {"raw": 484, "pct": 0.32155797101449274}, "kills_per_min": {"raw": 0.023337222870478413, "pct": 0.10416666666666667}, "last_hits_per_min": {"raw": 2.4270711785297547, "pct": 0.4936594202898551}, "hero_damage_per_min": {"raw": 468.16802800466746, "pct": 0.6322463768115942}, "hero_healing_per_min": {"raw": 10.2683780630105, "pct": 0.26358695652173914}, "tower_damage": {"raw": 0, "pct": 0.20018115942028986}}}, {"player_slot": 4, "team_number": 0, "team_slot": 4, "hero_id": 48, "hero_variant": 3, "item_0": 75, "item_1": 172, "item_2": 116, "item_3": 147, "item_4": 108, "item_5": 63, "backpack_0": 0, "backpack_1": 0, "backpack_2": 0, "item_neutral": 828, "item_neutral2": 1584, "kills": 7, "deaths": 12, "assists": 3, "leaver_status": 0, "last_hits": 307, "denies": 5, "gold_per_min": 510, "xp_per_min": 687, "level": 23, "net_worth": 17747, "aghanims_scepter": 0, "aghanims_shard": 0, "moonshard": 0, "hero_damage": 26776, "tower_damage": 244, "hero_healing": 0, "gold": 1042, "gold_spent": 18135, "ability_upgrades_arr": [5222, 5223, 5222, 5223, 5222, 5225, 5223, 5222, 5223, 1462, 7047, 5225, 1462, 1462, 770, 1462, 5225, 6180], "is_subscriber": false, "radiant_win": false, "start_time": 1763684619, "duration": 2571, "cluster": 346, "lobby_type": 0, "game_mode": 22, "is_contributor": false, "patch": 58, "region": 38, "isRadiant": true, "win": 0, "lose": 1, "total_gold": 21853, "total_xp": 29437, "kills_per_min": 0.1633605600933489, "kda": 0.77, "abandons": 0, "benchmarks": {"gold_per_min": {"raw": 510, "pct": 0.24965453707968677}, "xp_per_min": {"raw": 687, "pct": 0.3017042837402119}, "kills_per_min": {"raw": 0.16336056009334887, "pct": 0.3859972362966375}, "last_hits_per_min": {"raw": 7.1645274212368735, "pct": 0.2482726853984339}, "hero_damage_per_min": {"raw": 624.87747957993, "pct": 0.4177798249654537}, "hero_healing_per_min": {"raw": 0, "pct": 0.9686780285582681}, "tower_damage": {"raw": 244, "pct": 0.1510824504836481}}}, {"account_id": 65137360, "player_slot": 128, "team_number": 1, "team_slot": 0, "hero_id": 39, "hero_variant": 2, "item_0": 40, "item_1": 180, "item_2": 218, "item_3": 254, "item_4": 100, "item_5": 90, "backpack_0": 0, "backpack_1": 0, "backpack_2": 36, "item_neutral": 1607, "item_neutral2": 1585, "kills": 5, "deaths": 4, "assists": 38, "leaver_status": 0, "last_hits": 68, "denies": 5, "gold_per_min": 384, "xp_per_min": 745, "level": 24, "net_worth": 14220, "aghanims_scepter": 0, "aghanims_shard": 0, "moonshard": 0, "hero_damage": 20560, "tower_damage": 2774, "hero_healing": 192, "gold": 3435, "gold_spent": 13485, "ability_upgrades_arr": [5173, 5174, 5175, 5175, 5175, 5176, 5175, 5173, 5174, 5174, 6115, 5176, 5173, 5173, 5174, 629, 5176, 6856], "personaname": "PatoDeGoma", "name": null, "last_login": "2021-02-10T20:32:57.535Z", "rank_tier": 45, "computed_mmr": null, "is_subscriber": false, "radiant_win": false, "start_time": 1763684619, "duration": 2571, "cluster": 346, "lobby_type": 0, "game_mode": 22, "is_contributor": false, "patch": 58, "region": 38, "isRadiant": false, "win": 1, "lose": 0, "total_gold": 16454, "total_xp": 31923, "kills_per_min": 0.11668611435239207, "kda": 8.6, "abandons": 0, "benchmarks": {"gold_per_min": {"raw": 384, "pct": 0.1729936305732484}, "xp_per_min": {"raw": 745, "pct": 0.47337579617834397}, "kills_per_min": {"raw": 0.11668611435239205, "pct": 0.1505732484076433}, "last_hits_per_min": {"raw": 1.586931155192532, "pct": 0.04076433121019108}, "hero_damage_per_min": {"raw": 479.81330221703615, "pct": 0.1278980891719745}, "hero_healing_per_min": {"raw": 4.480746791131855, "pct": 0.9019108280254777}, "tower_damage": {"raw": 2774, "pct": 0.6354140127388535}}}, {"player_slot": 129, "team_number": 1, "team_slot": 1, "hero_id": 104, "hero_variant": 1, "item_0": 108, "item_1": 168, "item_2": 127, "item_3": 50, "item_4": 1, "item_5": 110, "backpack_0": 0, "backpack_1": 0, "backpack_2": 0, "item_neutral": 1599, "item_neutral2": 1584, "kills": 13, "deaths": 4, "assists": 27, "leaver_status": 0, "last_hits": 239, "denies": 16, "gold_per_min": 600, "xp_per_min": 900, "level": 26, "net_worth": 24703, "aghanims_scepter": 0, "aghanims_shard": 1, "moonshard": 0, "hero_damage": 33909, "tower_damage": 15704, "hero_healing": 11382, "gold": 1653, "gold_spent": 25490, "ability_upgrades_arr": [5595, 5596, 5597, 5597, 5595, 5598, 5595, 5596, 5597, 1176, 5596, 5598, 5595, 5596, 5597, 463, 5598, 7395, 925], "is_subscriber": false, "radiant_win": false, "start_time": 1763684619, "duration": 2571, "cluster": 346, "lobby_type": 0, "game_mode": 22, "is_contributor": false, "patch": 58, "region": 38, "isRadiant": false, "win": 1, "lose": 0, "total_gold": 25710, "total_xp": 38565, "kills_per_min": 0.30338389731621934, "kda": 8, "abandons": 0, "benchmarks": {"gold_per_min": {"raw": 600, "pct": 0.8422628951747089}, "xp_per_min": {"raw": 900, "pct": 0.8099833610648919}, "kills_per_min": {"raw": 0.30338389731621934, "pct": 0.7149750415973378}, "last_hits_per_min": {"raw": 5.57759626604434, "pct": 0.7372712146422629}, "hero_damage_per_min": {"raw": 791.3418903150525, "pct": 0.673377703826955}, "hero_healing_per_min": {"raw": 265.6242707117853, "pct": 0.9810316139767055}, "tower_damage": {"raw": 15704, "pct": 0.9875207986688852}}}, {"player_slot": 130, "team_number": 1, "team_slot": 2, "hero_id": 16, "hero_variant": 3, "item_0": 48, "item_1": 600, "item_2": 108, "item_3": 73, "item_4": 0, "item_5": 100, "backpack_0": 0, "backpack_1": 0, "backpack_2": 0, "item_neutral": 1642, "item_neutral2": 1597, "kills": 10, "deaths": 4, "assists": 25, "leaver_status": 0, "last_hits": 240, "denies": 3, "gold_per_min": 561, "xp_per_min": 893, "level": 25, "net_worth": 20474, "aghanims_scepter": 0, "aghanims_shard": 1, "moonshard": 0, "hero_damage": 26444, "tower_damage": 1323, "hero_healing": 0, "gold": 2379, "gold_spent": 19635, "ability_upgrades_arr": [5103, 5102, 5102, 1229, 5103, 5105, 5103, 5103, 5102, 1229, 1537, 5105, 1229, 1229, 5102, 890, 5105, 6872, 6207], "is_subscriber": false, "radiant_win": false, "start_time": 1763684619, "duration": 2571, "cluster": 346, "lobby_type": 0, "game_mode": 22, "is_contributor": false, "patch": 58, "region": 38, "isRadiant": false, "win": 1, "lose": 0, "total_gold": 24038, "total_xp": 38265, "kills_per_min": 0.23337222870478413, "kda": 7, "abandons": 0, "benchmarks": {"gold_per_min": {"raw": 561, "pct": 0.7039848197343453}, "xp_per_min": {"raw": 893, "pct": 0.7754585705249842}, "kills_per_min": {"raw": 0.2333722287047841, "pct": 0.6666666666666666}, "last_hits_per_min": {"raw": 5.600933488914819, "pct": 0.5895003162555345}, "hero_damage_per_min": {"raw": 617.1295215869312, "pct": 0.37254901960784315}, "hero_healing_per_min": {"raw": 0, "pct": 0.8798228969006958}, "tower_damage": {"raw": 1323, "pct": 0.7432005060088551}}}, {"account_id": 99393288, "player_slot": 131, "team_number": 1, "team_slot": 3, "hero_id": 55, "hero_variant": 2, "item_0": 1466, "item_1": 190, "item_2": 180, "item_3": 235, "item_4": 1, "item_5": 123, "backpack_0": 0, "backpack_1": 0, "backpack_2": 0, "item_neutral": 565, "item_neutral2": 1583, "kills": 12, "deaths": 6, "assists": 37, "leaver_status": 0, "last_hits": 211, "denies": 5, "gold_per_min": 589, "xp_per_min": 859, "level": 25, "net_worth": 24238, "aghanims_scepter": 0, "aghanims_shard": 0, "moonshard": 0, "hero_damage": 37996, "tower_damage": 3115, "hero_healing": 0, "gold": 2663, "gold_spent": 22255, "ability_upgrades_arr": [5256, 5255, 5255, 5256, 5255, 5258, 5255, 5256, 5256, 420, 5257, 5258, 5257, 5257, 6365, 5257, 5258, 6047, 6624], "personaname": "Mosman", "name": null, "last_login": null, "rank_tier": 43, "computed_mmr": 3968.58, "is_subscriber": false, "radiant_win": false, "start_time": 1763684619, "duration": 2571, "cluster": 346, "lobby_type": 0, "game_mode": 22, "is_contributor": false, "patch": 58, "region": 38, "isRadiant": false, "win": 1, "lose": 0, "total_gold": 25238, "total_xp": 36808, "kills_per_min": 0.28004667444574094, "kda": 7, "abandons": 0, "benchmarks": {"gold_per_min": {"raw": 589, "pct": 0.8875502008032129}, "xp_per_min": {"raw": 859, "pct": 0.8614457831325302}, "kills_per_min": {"raw": 0.28004667444574094, "pct": 0.8734939759036144}, "last_hits_per_min": {"raw": 4.924154025670945, "pct": 0.5582329317269076}, "hero_damage_per_min": {"raw": 886.7211201866978, "pct": 0.8755020080321285}, "hero_healing_per_min": {"raw": 0, "pct": 0.3815261044176707}, "tower_damage": {"raw": 3115, "pct": 0.9036144578313253}}}, {"account_id": 92377338, "player_slot": 132, "team_number": 1, "team_slot": 4, "hero_id": 101, "hero_variant": 2, "item_0": 116, "item_1": 21, "item_2": 273, "item_3": 48, "item_4": 77, "item_5": 256, "backpack_0": 23, "backpack_1": 0, "backpack_2": 0, "item_neutral": 1638, "item_neutral2": 1597, "kills": 14, "deaths": 9, "assists": 20, "leaver_status": 0, "last_hits": 174, "denies": 7, "gold_per_min": 535, "xp_per_min": 756, "level": 24, "net_worth": 20732, "aghanims_scepter": 0, "aghanims_shard": 1, "moonshard": 0, "hero_damage": 29585, "tower_damage": 1715, "hero_healing": 0, "gold": 577, "gold_spent": 21770, "ability_upgrades_arr": [5582, 5581, 5581, 5582, 5581, 5584, 5581, 5583, 5582, 5582, 411, 5584, 5583, 5583, 6181, 5583, 5584, 6885], "personaname": "Rodrinstein", "name": null, "last_login": null, "rank_tier": 31, "computed_mmr": 3802.18, "is_subscriber": false, "radiant_win": false, "start_time": 1763684619, "duration": 2571, "cluster": 346, "lobby_type": 0, "game_mode": 22, "is_contributor": false, "patch": 58, "region": 38, "isRadiant": false, "win": 1, "lose": 0, "total_gold": 22924, "total_xp": 32394, "kills_per_min": 0.3267211201866978, "kda": 3.4, "abandons": 0, "benchmarks": {"gold_per_min": {"raw": 535, "pct": 0.9155509783728115}, "xp_per_min": {"raw": 756, "pct": 0.7855303810504635}, "kills_per_min": {"raw": 0.32672112018669774, "pct": 0.8501544799176107}, "last_hits_per_min": {"raw": 4.060676779463243, "pct": 0.878475798146241}, "hero_damage_per_min": {"raw": 690.4317386231038, "pct": 0.6315653964984552}, "hero_healing_per_min": {"raw": 0, "pct": 0.7868177136972193}, "tower_damage": {"raw": 1715, "pct": 0.8867147270854789}}}], "radiant_win": false, "duration": 2571, "pre_game_duration": 90, "start_time": 1763684619, "match_id": 8568682090, "match_seq_num": 7196563711, "tower_status_radiant": 0, "tower_status_dire": 1974, "barracks_status_radiant": 0, "barracks_status_dire": 63, "cluster": 346, "first_blood_time": 82, "lobby_type": 0, "human_players": 10, "leagueid": 0, "game_mode": 22, "flags": 1, "engine": 1, "radiant_score": 27, "dire_score": 54, "picks_bans": [{"is_pick": true, "hero_id": 39, "team": 1, "order": 0}, {"is_pick": true, "hero_id": 55, "team": 1, "order": 1}, {"is_pick": true, "hero_id": 102, "team": 0, "order": 2}, {"is_pick": true, "hero_id": 48, "team": 0, "order": 3}, {"is_pick": true, "hero_id": 104, "team": 1, "order": 4}, {"is_pick": true, "hero_id": 101, "team": 1, "order": 5}, {"is_pick": true, "hero_id": 64, "team": 0, "order": 6}, {"is_pick": true, "hero_id": 9, "team": 0, "order": 7}, {"is_pick": true, "hero_id": 14, "team": 0, "order": 8}, {"is_pick": true, "hero_id": 16, "team": 1, "order": 9}, {"is_pick": false, "hero_id": 61, "team": 0, "order": 10}, {"is_pick": false, "hero_id": 136, "team": 0, "order": 11}, {"is_pick": false, "hero_id": 128, "team": 0, "order": 12}, {"is_pick": false, "hero_id": 131, "team": 0, "order": 13}, {"is_pick": false, "hero_id": 42, "team": 0, "order": 14}, {"is_pick": false, "hero_id": 26, "team": 1, "order": 15}], "od_data": {"has_api": true, "has_gcdata": false, "has_parsed": false, "has_archive": false}, "metadata": null, "patch": 58, "region": 38}